caver/__init__.py
caver/classify.py
caver/config.py
caver/data.py
caver/ensemble.py
caver/evaluate.py
caver/evaluator.py
caver/process.py
caver/utils.py
caver/model/__init__.py
caver/model/base.py
caver/model/cavermodel.py
caver/model/cnn.py
caver/model/fasttext.py
caver/model/han.py
caver/model/lstm.py
caver/model/swen.py
caver-0.2.dist-info/METADATA
caver-0.2.dist-info/WHEEL
caver-0.2.dist-info/entry_points.txt
caver-0.2.dist-info/top_level.txt
caver-0.2.dist-info/RECORD
